2022.2/VALMIRFERREIRADASILVA_119211110/Sprint3/RegisterFile.sv
module RegisterFile#(parameter WIDTH = 8)(
    input logic             clk,
                            we3,
    input logic [2:0]       ra1,
                            ra2,
                            wa3,
    input logic  [WIDTH-1:0] wd3,
    output logic [WIDTH-1:0] rd1,
                            rd2  

);
    logic [WIDTH-1:0] mem[WIDTH-1:0];
    initial mem[0] = 0;
    always_ff@(posedge clk)
        if(we3) mem[wa3] <= (wa3 == 3'b0) ? 3'b0 : wd3;
    assign rd1 = mem[ra1];
    assign rd2 = mem[ra2];
endmodule

2022.2/VALMIRFERREIRADASILVA_119211110/Sprint3/testbench.sv
`include "./RegisterFile.sv"
module tb;
    parameter WIDTH = 8;
    logic           clk;
    logic           we3;
    logic [2:0]     ra1,
                    ra2,
                    wa3;
    logic [WIDTH-1:0] rd1,
                    rd2,
                    wd3;
    RegisterFile #(  .WIDTH     (       WIDTH      ))
    meu_registrador(    
                    .clk        (       clk        ),
                    .we3        (       we3        ),
                    .ra1        (       ra1        ),
                    .ra2        (       ra2        ),
                    .wa3        (       wa3        ),
                    .rd1        (       rd1        ),
                    .wd3        (       wd3        )
    );

    always #1 clk = ~clk;
    initial begin
        $dumpfile   ("Graphic_Register.vcd");
        $dumpvars   (0,meu_registrador     );   
        clk = 0;
        #1@(negedge clk) {we3,ra1,ra2,wa3,wd3} = 18'b0_000_000_000_00001010;
        #1@(negedge clk) {we3,ra1,ra2,wa3,wd3} = 18'b1_000_000_001_10001010;
        #1@(negedge clk) {we3,ra1,ra2,wa3,wd3} = 18'b1_001_000_010_10101010;
        #1@(negedge clk) {we3,ra1,ra2,wa3,wd3} = 18'b1_010_001_011_11001010;
        #1@(negedge clk) {we3,ra1,ra2,wa3,wd3} = 18'b1_011_010_100_11101010;
        #1@(negedge clk) {we3,ra1,ra2,wa3,wd3} = 18'b1_100_011_101_10101010;
        #1@(negedge clk) {we3,ra1,ra2,wa3,wd3} = 18'b1_101_100_110_10001110;
        #1@(negedge clk) {we3,ra1,ra2,wa3,wd3} = 18'b1_000_101_111_11111111;

        #1@(negedge clk) {we3,ra1,ra2,wa3,wd3} = 18'b1_011_011_011_10001010;


        #20$finish;
    end
endmodule

2022.2/VALMIRFERREIRADASILVA_119211110/Sprint3/Graphic_Register.vcd
$date
	Fri Mar 24 22:39:02 2023
$end
$version
	Icarus Verilog
$end
$timescale
	1s
$end
$scope module tb $end
$scope module meu_registrador $end
$var wire 1 ! clk $end
$var wire 3 " ra1 [2:0] $end
$var wire 3 # ra2 [2:0] $end
$var wire 8 $ rd1 [7:0] $end
$var wire 8 % rd2 [7:0] $end
$var wire 3 & wa3 [2:0] $end
$var wire 8 ' wd3 [7:0] $end
$var wire 1 ( we3 $end
$upscope $end
$upscope $end
$enddefinitions $end
#0
$dumpvars
x(
bx '
bx &
bx %
bx $
bx #
bx "
0!
$end
#1
1!
#2
0(
b0 $
b0 "
b0 %
b0 #
b0 &
b1010 '
0!
#3
1!
#4
1(
b1 &
b10001010 '
0!
#5
1!
#6
b10001010 $
b1 "
b10 &
b10101010 '
0!
#7
1!
#8
b10101010 $
b10 "
b10001010 %
b1 #
b11 &
b11001010 '
0!
#9
1!
#10
b11001010 $
b11 "
b10101010 %
b10 #
b100 &
b11101010 '
0!
#11
1!
#12
b11101010 $
b100 "
b11001010 %
b11 #
b101 &
b10101010 '
0!
#13
1!
#14
b10101010 $
b101 "
b11101010 %
b100 #
b110 &
b10001110 '
0!
#15
1!
#16
b0 $
b0 "
b10101010 %
b101 #
b111 &
b11111111 '
0!
#17
1!
#18
b11001010 $
b11 "
b11001010 %
b11 #
b11 &
b10001010 '
0!
#19
b10001010 $
b10001010 %
1!
