2022.2/VALMIRFERREIRADASILVA_119211110/Sprint2/count_M10.sv
module count_M10(
    input logic  clk,
            rst,
    output logic [3:0] counter_value
);
    always_ff@(posedge clk)begin
        if(rst) counter_value = 0;
        else if(counter_value == 9) counter_value <=  0;
        else                         counter_value <= counter_value + 1; 
    end
endmodule

2022.2/VALMIRFERREIRADASILVA_119211110/Sprint2/testbench_count_M10.sv
`include "./count_M10.sv"
module tb;
    logic clk,
          rst;
    logic [3:0] counter_value;
    logic [3:0] pass_test, fail_test;
    count_M10 my_count(

        .clk           (   clk                      ),
        .rst           (   rst                      ),
        .counter_value (        counter_value       )
    );
    task expect_output_counter(
        input [3:0] counter_value_exp
    ); 

        if(counter_value_exp == counter_value) pass_test+=1;
        else fail_test+=1;
        $display("   %b    : %b     ", counter_value,counter_value_exp);

    endtask
    always #1 clk = ~clk;
    initial begin
        clk = 0;
        pass_test = 0;
        fail_test = 0;
        $dumpfile("count_M10.vcd");
        $dumpvars(0,my_count);
        $display("obtained : expected");
        @(posedge clk) rst = 1; #1 expect_output_counter(0);
        @(posedge clk) rst = 0; #1 expect_output_counter(1);
        @(posedge clk) rst = 0; #1 expect_output_counter(2);
        @(posedge clk) rst = 0; #1 expect_output_counter(3);
        @(posedge clk) rst = 0; #1 expect_output_counter(4);
        @(posedge clk) rst = 0; #1 expect_output_counter(5);
        @(posedge clk) rst = 0; #1 expect_output_counter(6);
        @(posedge clk) rst = 0; #1 expect_output_counter(7);
        @(posedge clk) rst = 0; #1 expect_output_counter(8);
        @(posedge clk) rst = 0; #1 expect_output_counter(9);
        @(posedge clk) rst = 1; #1 expect_output_counter(0);
        @(posedge clk) rst = 0; #1 expect_output_counter(1);


        

        $display("\n-------------status test-------------\n");
        $display("pass | fail");
        $display(" %d  |  %d ", pass_test, fail_test);
        #20 $finish;
    end
endmodule

2022.2/VALMIRFERREIRADASILVA_119211110/Sprint2/count_M10.vcd
$date
	Fri Mar 24 15:34:36 2023
$end
$version
	Icarus Verilog
$end
$timescale
	1s
$end
$scope module tb $end
$scope module my_count $end
$var wire 1 ! clk $end
$var wire 1 " rst $end
$var reg 4 # counter_value [3:0] $end
$upscope $end
$upscope $end
$enddefinitions $end
#0
$dumpvars
bx #
x"
0!
$end
#1
b0 #
1"
1!
#2
0!
#3
b1 #
0"
1!
#4
0!
#5
b10 #
1!
#6
0!
#7
b11 #
1!
#8
0!
#9
b100 #
1!
#10
0!
#11
b101 #
1!
#12
0!
#13
b110 #
1!
#14
0!
#15
b111 #
1!
#16
0!
#17
b1000 #
1!
#18
0!
#19
b1001 #
1!
#20
0!
#21
b0 #
1"
1!
#22
0!
#23
b1 #
0"
1!
#24
0!
#25
b10 #
1!
#26
0!
#27
b11 #
1!
#28
0!
#29
b100 #
1!
#30
0!
#31
b101 #
1!
#32
0!
#33
b110 #
1!
#34
0!
#35
b111 #
1!
#36
0!
#37
b1000 #
1!
#38
0!
#39
b1001 #
1!
#40
0!
#41
b1010 #
1!
#42
0!
#43
b0 #
1!
