2022.2/VALMIRFERREIRADASILVA_119211110/Sprint2/decod_hexa2_7seg.sv
module decod_hexa2_7seg(
    input logic [3:0]  bincode,
    output logic [6:0] pinoutdisplay7segment
);
    logic [6:0] map_leds[15:0];
    assign map_leds[ 0] = 7'b111_1110;
    assign map_leds[ 1] = 7'b011_0000;
    assign map_leds[ 2] = 7'b110_1101;
    assign map_leds[ 3] = 7'b111_1001;
    assign map_leds[ 4] = 7'b011_1011;
    assign map_leds[ 5] = 7'b101_1011;
    assign map_leds[ 6] = 7'b101_1111;
    assign map_leds[ 7] = 7'b111_0000;
    assign map_leds[ 8] = 7'b111_1111;
    assign map_leds[ 9] = 7'b111_1011;
    assign map_leds[10] = 7'b111_0111;
    assign map_leds[11] = 7'b001_1111;
    assign map_leds[12] = 7'b100_1110;
    assign map_leds[13] = 7'b011_1101; 
    assign map_leds[14] = 7'b100_1111;
    assign map_leds[15] = 7'b100_0111;
    always_comb pinoutdisplay7segment = map_leds[bincode];
endmodule

2022.2/VALMIRFERREIRADASILVA_119211110/Sprint2/testebench_decod_hex.sv
`include "./decod_hexa2_7seg.sv"
module tb;
    logic [3:0] bincode;
    logic [6:0] pinoutdisplay7segment;
    logic [4:0] pass_fail, pass_test;
    decod_hexa2_7seg display7segment(
        .bincode                (       bincode                 ),
        .pinoutdisplay7segment  (       pinoutdisplay7segment   )
    );

    task expect_output(
        input [6:0] pinoutdisplay7segment_expect);
        begin   
            if(pinoutdisplay7segment == pinoutdisplay7segment_expect)
                pass_test+=1;
            else begin
                pass_fail+=1;
                $display("%d %b %b",bincode,pinoutdisplay7segment,pinoutdisplay7segment_expect);
            end
        end
    endtask

    initial begin
        pass_fail = 0;
        pass_test = 0;
        $display("expected  : obtained");
        $dumpfile("decod_hex2_7seg.vcd");
        $dumpvars(0,display7segment);
        bincode = 0; #1expect_output(7'b1111110);
        bincode = 1; #1expect_output(7'b0110000);
        bincode = 2; #1expect_output(7'b1101101);
        bincode = 3; #1expect_output(7'b1111001);
        bincode = 4; #1expect_output(7'b0111011);
        bincode = 5; #1expect_output(7'b1011011);
        bincode = 6; #1expect_output(7'b1011111);
        bincode = 7; #1expect_output(7'b1110000);
        bincode = 8; #1expect_output(7'b1111111);
        bincode = 9; #1expect_output(7'b1111011);
        $display("pass : fail");
        $display("%d    : %d ",pass_test,pass_fail);
    end

endmodule

2022.2/VALMIRFERREIRADASILVA_119211110/Sprint2/decod_hex2_7seg.vcd
$date
	Thu Mar 23 17:01:41 2023
$end
$version
	Icarus Verilog
$end
$timescale
	1s
$end
$scope module tb $end
$scope module display7segment $end
$var wire 4 ! bincode [3:0] $end
$var reg 7 " pinoutdisplay7segment [6:0] $end
$upscope $end
$upscope $end
$enddefinitions $end
#0
$dumpvars
b1111110 "
b0 !
$end
#1
b110000 "
b1 !
#2
b1101101 "
b10 !
#3
b1111001 "
b11 !
#4
b111011 "
b100 !
#5
b1011011 "
b101 !
#6
b1011111 "
b110 !
#7
b1110000 "
b111 !
#8
b1111111 "
b1000 !
#9
b1111011 "
b1001 !
