2022.2/testes/design.sv
// Code your design here
module p(
  input logic [7:0] din,
  input logic rst,
  output logic  d,
  output logic [7:0] dout
);
  always@(*) begin
    if(rst) dout = din;
    else begin
      d = dout[0];
      dout = {1'b0,dout[7:1]};
    end
  end

endmodule

2022.2/testes/testbench.sv
// Code your testbench here
// or browse Examples

`include "./design.sv"
module tb;
  
  logic [7:0] din,dout;
  logic d,rst;
  p p1(
    .din(din),
    .d(d),
    .dout(dout),
    .rst(rst)
  );
  initial rst = 1;
      always #1 rst = ~ rst;  
  initial begin
    $dumpfile("a.vcd");
    $dumpvars(0,p1);
      din = 1111_1110;#1
      din = 0000_0000;#1
      din = 1111_1111;#1
      din = 0000_0000;#1
      din = 1111_1110;#1
      din = 0000_0000;#1
      din = 1111_1111;#1
      din = 0000_0000;#1
      #1$finish;
  end
endmodule

2022.2/testes/a.vcd
$date
	Tue Apr 18 01:58:49 2023
$end
$version
	Icarus Verilog
$end
$timescale
	1s
$end
$scope module tb $end
$scope module p1 $end
$var wire 8 ! din [7:0] $end
$var wire 1 " rst $end
$var reg 1 # d $end
$var reg 8 $ dout [7:0] $end
$upscope $end
$upscope $end
$enddefinitions $end
#0
$dumpvars
b11000110 $
x#
1"
b11000110 !
$end
#1
b1100011 $
0#
b0 !
0"
#2
b11000111 $
b11000111 !
1"
#3
b1100011 $
1#
b0 !
0"
#4
b11000110 $
b11000110 !
1"
#5
b1100011 $
0#
b0 !
0"
#6
b11000111 $
b11000111 !
1"
#7
b1100011 $
1#
b0 !
0"
#8
b0 $
1"
#9
0#
0"
