2022.2/VALMIRFERREIRADASILVA_119211110/desafios ads/regdeslo.sv
module regdeslo(
    input logic  clk,
                 rst,
                 in_serial,
    input  logic [1:0] op,
    input  logic [7:0] in_paralelo,
    output logic [7:0] outreg
);
    logic [7:0] reg_int;
    always@* case(op)
        0:reg_int = outreg;
        1:reg_int = reg_int << in_serial;
        2:reg_int = reg_int >> in_serial;
        3:reg_int = in_paralelo;
    endcase

    always_ff @( posedge clk ) begin 
        outreg <= rst ? 0: reg_int;
    end
endmodule

2022.2/VALMIRFERREIRADASILVA_119211110/desafios ads/test_reg.sv
`include "./regdeslo.sv"
module tb;
    logic [20:0] caso_de_testes[5:0];
    logic [30:0] operac[5:0];
    logic [3:0] test_fail,
                test_pass;
    logic       clk         ,
                rst         ,
                in_serial   ;
    logic [1:0] op          ;
    logic [7:0] in_paralelo ,
                outreg      ;
    regdeslo inst1regdesloc(
        .clk        (       clk         ),
        .rst        (       rst         ),
        .in_serial  (       in_serial   ),
        .op         (       op          ),
        .in_paralelo(       in_paralelo ),
        .outreg     (       outreg      )
    );
    initial clk = 0;
    always #1 clk = ~clk;

    task expected_out_test(
        input [7:0] valor_esperado
    );
        if(valor_esperado == outreg)
            test_pass += 1;
        else
            test_fail +=1;
        $display("%b %b, status op %s :%s",valor_esperado,outreg,operac[op],valor_esperado == outreg ? "pass":"fail");
        // $display("%d",outreg);
    endtask
    initial begin
        test_pass = 0;
        test_fail = 0;
        operac[0] = "NOP";
        operac[1] = "SHL";
        operac[2] = "SHR";
        operac[3] = "LOAD";

        $readmemb("casos_de_testes.txt",caso_de_testes);
        $dumpfile("myReg.vcd");
        $dumpvars(0,inst1regdesloc);
        $display("esperado, obtido");
        for(integer i =0; i < 4; i++)begin
            @(negedge clk) {in_paralelo,in_serial,op,rst} = caso_de_testes[i][12:0]; #2expected_out_test(caso_de_testes[i][20:12]);
        end
    end
    initial #100 $finish;

endmodule

2022.2/VALMIRFERREIRADASILVA_119211110/desafios ads/myReg.vcd
$date
	Sun Apr 16 19:52:36 2023
$end
$version
	Icarus Verilog
$end
$timescale
	1s
$end
$scope module tb $end
$scope module inst1regdesloc $end
$var wire 1 ! clk $end
$var wire 8 " in_paralelo [7:0] $end
$var wire 1 # in_serial $end
$var wire 2 $ op [1:0] $end
$var wire 1 % rst $end
$var reg 8 & outreg [7:0] $end
$var reg 8 ' reg_int [7:0] $end
$upscope $end
$upscope $end
$enddefinitions $end
#0
$dumpvars
bx '
bx &
x%
bx $
x#
bx "
0!
$end
#1
1!
#2
b0 '
b0 "
0#
b11 $
1%
0!
#3
b0 &
1!
#4
b11111111 '
b11111111 "
0%
0!
#5
b11111111 &
1!
#6
b11111110 '
1#
b1 $
0!
#7
b11111100 '
b11111110 &
1!
#8
b1111110 '
b10 $
0!
#9
b111111 '
b1111110 &
1!
#10
0!
#11
b11111 '
b111111 &
1!
#12
0!
#13
b1111 '
b11111 &
1!
#14
0!
#15
b111 '
b1111 &
1!
#16
0!
#17
b11 '
b111 &
1!
#18
0!
#19
b1 '
b11 &
1!
#20
0!
#21
b0 '
b1 &
1!
#22
0!
#23
b0 &
1!
