2022.2/VALMIRFERREIRADASILVA_119211110/desafios ads/piramide.sv
module piramide(
    input  logic clk,
                 rst,
    input  logic [3:0] max,
    output logic [3:0] outputM_
);

    logic S, R, qLatch;
    logic [3:0] outputM;
    assign      S = (outputM== 15); // ~ set value latch
    assign      R = (outputM ==       0); // Reset value latch
    always_comb begin : Latch_RS
        case({S,R})
            1:qLatch = 0;
            2:qLatch = 1;
            default:qLatch = qLatch;
        endcase
    end
    always_ff @(posedge clk ) begin : FFD
        if(rst) begin
            outputM <= 0;
            qLatch  <= 0;
        end
        else
            outputM <= (qLatch) ?  (outputM - 1):(outputM + 1);
    end
    assign      outputM_ = outputM  < max ? outputM : max;
endmodule

2022.2/VALMIRFERREIRADASILVA_119211110/desafios ads/test.sv
`include "./piramide.sv"
module tb;

    logic clk, rst;
    logic [3:0] max ,
                outp;
    
    piramide instp(
            .clk    (   clk  ),
            .max    (   max  ),
            .outputM_(   outp ),
            .rst    (   rst )

    );
    always #1clk = ~clk;
    initial begin
        clk = 0;

        $dumpfile("pi.vcd");
        $dumpvars (0,instp);
        @(negedge clk) {rst,max} =  5'b10111;
        @(negedge clk) {rst,max} =  5'b00100;


        #100 $finish;
    end
    
endmodule

2022.2/VALMIRFERREIRADASILVA_119211110/desafios ads/pi.vcd
$date
	Fri Mar 31 13:29:45 2023
$end
$version
	Icarus Verilog
$end
$timescale
	1s
$end
$scope module tb $end
$scope module instp $end
$var wire 1 ! clk $end
$var wire 4 " max [3:0] $end
$var wire 1 # rst $end
$var wire 4 $ outputM_ [3:0] $end
$var wire 1 % S $end
$var wire 1 & R $end
$var reg 4 ' outputM [3:0] $end
$var reg 1 ( qLatch $end
$scope begin FFD $end
$upscope $end
$scope begin Latch_RS $end
$upscope $end
$upscope $end
$upscope $end
$enddefinitions $end
#0
$dumpvars
x(
bx '
x&
x%
bx $
x#
bx "
0!
$end
#1
1!
#2
1#
b111 "
0!
#3
b0 $
0(
0%
1&
b0 '
1!
#4
0#
b100 "
0!
#5
b1 $
0&
b1 '
1!
#6
0!
#7
b10 $
b10 '
1!
#8
0!
#9
b11 $
b11 '
1!
#10
0!
#11
b100 $
b100 '
1!
#12
0!
#13
b101 '
1!
#14
0!
#15
b110 '
1!
#16
0!
#17
b111 '
1!
#18
0!
#19
b1000 '
1!
#20
0!
#21
b1001 '
1!
#22
0!
#23
b1010 '
1!
#24
0!
#25
b1011 '
1!
#26
0!
#27
b1100 '
1!
#28
0!
#29
b1101 '
1!
#30
0!
#31
b1110 '
1!
#32
0!
#33
1(
1%
b1111 '
1!
#34
0!
#35
0%
b1110 '
1!
#36
0!
#37
b1101 '
1!
#38
0!
#39
b1100 '
1!
#40
0!
#41
b1011 '
1!
#42
0!
#43
b1010 '
1!
#44
0!
#45
b1001 '
1!
#46
0!
#47
b1000 '
1!
#48
0!
#49
b111 '
1!
#50
0!
#51
b110 '
1!
#52
0!
#53
b101 '
1!
#54
0!
#55
b100 '
1!
#56
0!
#57
b11 $
b11 '
1!
#58
0!
#59
b10 $
b10 '
1!
#60
0!
#61
b1 $
b1 '
1!
#62
0!
#63
0(
b0 $
1&
b0 '
1!
#64
0!
#65
b1 $
0&
b1 '
1!
#66
0!
#67
b10 $
b10 '
1!
#68
0!
#69
b11 $
b11 '
1!
#70
0!
#71
b100 $
b100 '
1!
#72
0!
#73
b101 '
1!
#74
0!
#75
b110 '
1!
#76
0!
#77
b111 '
1!
#78
0!
#79
b1000 '
1!
#80
0!
#81
b1001 '
1!
#82
0!
#83
b1010 '
1!
#84
0!
#85
b1011 '
1!
#86
0!
#87
b1100 '
1!
#88
0!
#89
b1101 '
1!
#90
0!
#91
b1110 '
1!
#92
0!
#93
1(
1%
b1111 '
1!
#94
0!
#95
0%
b1110 '
1!
#96
0!
#97
b1101 '
1!
#98
0!
#99
b1100 '
1!
#100
0!
#101
b1011 '
1!
#102
0!
#103
b1010 '
1!
